{
  "id": "link-ocarina-of-time-amiibo",
  "name": "Link • Ocarina of Time",
  "cover": "https://amiibo.life/assets/figures/amiibo/the-legend-of-zelda/link-ocarina-of-time-52f7c96d458974410ffce13239a6fbe7d2d051aa4b0e6e82cc255e6903138878.png",
  "release": "2016-12-01",
  "type": "amiibo",
  "franchise": {
    "series": "The Legend of Zelda",
    "subseries": null
  },
  "amiibo": {
    "number": null,
    "wave": "The Legend of Zelda Wave 2: 30th Anniversary"
  },
  "ownership": "owned",
  "functionality": [
    {
      "game": "the-legend-of-zelda-tears-of-the-kingdom",
      "effect": "Receive the Lon Lon Ranch Fabric | Receive materials and a weapon or rare item"
    },
    {
      "game": "the-legend-of-zelda-breath-of-the-wild",
      "effect": "Receive materials and a rare or exclusive item"
    },
    {
      "game": "hyrule-warriors-age-of-imprisonment",
      "effect": "Receive specific crafting materials or a weapon for the character"
    },
    {
      "game": "the-legend-of-zelda-echoes-of-wisdom",
      "effect": "Unlock an amiibo-exclusive outfit / Receive smoothie ingredients"
    },
    {
      "game": "hyrule-warriors-age-of-calamity",
      "effect": "Receive specific crafting materials or a weapon for the character"
    },
    {
      "game": "super-smash-bros-ultimate",
      "effect": "Battle and train up a computer-controlled Figure Player of the character (Read+Write)"
    },
    {
      "game": "hyrule-warriors-definitive-edition",
      "effect": "Receive a weapon rated 3 stars or higher"
    },
    {
      "game": "bayonetta-2",
      "effect": "Unlock a costume based on the character (short-hair version)"
    },
    {
      "game": "mario-kart-8-deluxe",
      "effect": "Unlock a Legend of Zelda-themed Mii racing suit"
    },
    {
      "game": "kirby-planet-robobot",
      "effect": "Give Kirby a Copy ability based on the character's abilities and a health item"
    },
    {
      "game": "the-legend-of-zelda-twilight-princess-hd",
      "effect": "Get a refill of arrows, once a day per amiibo"
    },
    {
      "game": "hyrule-warriors-legends",
      "effect": "Receive a weapon rated 3 stars or higher"
    },
    {
      "game": "hyrule-warriors",
      "effect": "Unlock the amiibo-exclusive Spinner weapon | Receive a weapon rated 3 stars or higher"
    }
  ],
  "event": null,
  "notes": null
}
