{"id":"sonic-superstars","name":"Sonic Superstars","cover":"sonic-superstars","release":"2023-10-17","type":"game","franchise":{"universe":"Sonic","series":"Sonic Boost","subseries":null},"classification":{"genres":["Action","Platform"],"subgenres":["2.5D Platformer"],"themes":[],"tags":["Modern","Co-op"]},"player_age":6,"access":[{"platform":"nintendo-switch","via":null,"format":"physical","status":"owned","notes":null}],"versions":[],"relationships":[{"source":"sonic-generations-3ds","type":"sequel"},{"source":"sonic-generations-2024","type":"sequel"}],"playstyle":{"players":{"min":1,"max":4},"modes":["solo","co_op"]},"companies":["Arzest","Sonic Team"],"progress":"planned","backlog":{"priority":4,"reason":"Modern attempt at classic-style Sonic gameplay.","rating":4,"difficulty":2,"estimated_hours":8},"acquisition":{"priority":null,"reason":null,"notes":null},"event":null,"notes":null}