{
  "id": "c64-mini",
  "name": "The C64 Mini",
  "cover": "c64-mini",
  "release": "2018-01-29",
  "type": "hardware",
  "franchise": {
    "series": "Commodore",
    "subseries": "Commodore 64"
  },
  "companies": {
    "manufacturer": [
      "Retro Games Ltd"
    ],
    "publisher": [
      "Retro Games Ltd"
    ]
  },
  "hardware": {
    "category": "computer",
    "form": "dedicated",
    "primary_family": "c64-mini",
    "compatible_families": [],
    "generation": null,
    "era": "8-bit",
    "compatible_with": []
  },
  "variants": [],
  "ownership": [
    {
      "variant": null,
      "status": "wishlist",
      "notes": null
    }
  ],
  "acquisition": {
    "priority": 4,
    "reason": "Covers early home computer era cleanly",
    "notes": null
  },
  "contains": [],
  "event": null,
  "notes": null
}
