{
    "id": "mario-and-luigi-superstar-saga-plus-bowsers-minions",
    "name": "Mario & Luigi: Superstar Saga + Bowser's Minions",
    "cover": "https://images.igdb.com/igdb/image/upload/t_cover_big/co22a7.webp",
    "release": "2017-10-06",
    "type": "bundle",
    "franchise": {
        "universe": "Mario",
        "series": "Mario & Luigi",
        "subseries": null
    },
    "classification": {
        "genres": [
            "RPG"
        ],
        "subgenres": [],
        "themes": [
            "Fantasy",
            "Comedy"
        ],
        "tags": [
            "Bundle"
        ]
    },
    "player_age": 8,
    "access": [
        {
            "platform": "nintendo-3ds",
            "via": null,
            "format": "physical",
            "status": "owned",
            "notes": null
        }
    ],
    "versions": [],
    "relationships": [],
    "playstyle": {
        "players": {
            "min": 1,
            "max": 1
        },
        "modes": [
            "solo"
        ]
    },
    "companies": {
        "developer": [
            "AlphaDream"
        ],
        "publisher": [
            "Nintendo"
        ]
    },
    "progress": "planned",
    "backlog": {
        "priority": 3,
        "reason": "Definitive packaged version of Superstar Saga with extra content.",
        "rating": 4,
        "difficulty": 3,
        "estimated_hours": 25
    },
    "acquisition": {
        "priority": null,
        "reason": null,
        "notes": null
    },
    "event": null,
    "notes": null,
    "contains": [
        "mario-and-luigi-superstar-saga-3ds",
        "minion-quest-the-search-for-bowser"
    ]
}
