{
    "id": "super-smash-bros-brawl",
    "name": "Super Smash Bros. Brawl",
    "cover": "https://images.igdb.com/igdb/image/upload/t_cover_big/co60ua.webp",
    "release": "2008-01-31",
    "type": "game",
    "franchise": {
        "universe": "Super Smash Bros.",
        "series": "Super Smash Bros.",
        "subseries": null
    },
    "classification": {
        "genres": [
            "Fighting"
        ],
        "subgenres": [
            "Platform Fighter"
        ],
        "themes": [
            "Crossover",
            "Nintendo"
        ],
        "tags": [
            "Party Fighter",
            "Story Mode"
        ]
    },
    "player_age": 8,
    "access": [
        {
            "platform": "nintendo-wii",
            "via": null,
            "format": "physical",
            "status": "owned",
            "notes": null
        }
    ],
    "versions": [],
    "relationships": [
        {
            "source": "super-smash-bros-melee",
            "type": "prequel"
        },
        {
            "source": "super-smash-bros-for-wii-u",
            "type": "sequel"
        }
    ],
    "playstyle": {
        "players": {
            "min": 1,
            "max": 4
        },
        "modes": [
            "solo",
            "versus",
            "party",
            "online",
            "co_op"
        ]
    },
    "companies": {
        "developer": [
            "Sora Ltd.",
            "Game Arts"
        ],
        "publisher": [
            "Nintendo"
        ]
    },
    "progress": "planned",
    "backlog": {
        "priority": 5,
        "reason": "Massive crossover celebration with extensive content and memorable single-player modes.",
        "rating": 5,
        "difficulty": 2,
        "estimated_hours": 40
    },
    "acquisition": {
        "priority": 5,
        "reason": "Historically significant Nintendo crossover and major Wii multiplayer title.",
        "notes": null
    },
    "event": null,
    "notes": null
}